README.rst
setup.cfg
setup.py
graphiti/__init__.py
graphiti/aggregation.py
graphiti/client.py
graphiti/cmd.py
graphiti/example.py
graphiti/tests.py
graphiti.egg-info/PKG-INFO
graphiti.egg-info/SOURCES.txt
graphiti.egg-info/dependency_links.txt
graphiti.egg-info/entry_points.txt
graphiti.egg-info/requires.txt
graphiti.egg-info/top_level.txt
graphiti.egg-info/zip-safe